timekit/__init__.py
timekit/api.py
timekit/factor.py
timekit/parser.py
timekit/timekit.py
timekit-0.1.3.dist-info/LICENSE
timekit-0.1.3.dist-info/METADATA
timekit-0.1.3.dist-info/WHEEL
timekit-0.1.3.dist-info/top_level.txt
timekit-0.1.3.dist-info/RECORD
